pyswarming/__init__.py
pyswarming/behaviors.py
pyswarming/swarm.py
tests/__init__.py
tests/test_behaviors.py
tests/test_swarm.py
pyswarming-1.1.5.dist-info/LICENSE.md
pyswarming-1.1.5.dist-info/METADATA
pyswarming-1.1.5.dist-info/WHEEL
pyswarming-1.1.5.dist-info/top_level.txt
pyswarming-1.1.5.dist-info/RECORD
