Metadata-Version: 2.1
Name: pyswarming
Version: 1.1.5
Summary: A research toolkit for Swarm Robotics
Home-page: https://github.com/mrsonandrade/pyswarming
Author: Emerson Martins de Andrade
Author-email: mrson@oceanica.ufrj.br
Classifier: Programming Language :: Python :: 3.7
Classifier: Programming Language :: Python :: 3.8
Classifier: Programming Language :: Python :: 3.9
Classifier: Programming Language :: Python :: 3.10
Classifier: Programming Language :: Python :: 3.11
Classifier: License :: OSI Approved :: BSD License
Classifier: Intended Audience :: Science/Research
Classifier: Operating System :: OS Independent
Classifier: Topic :: Scientific/Engineering :: GIS
Requires-Python: >=3.7
License-File: LICENSE.md
Requires-Dist: numpy
Requires-Dist: numdifftools
Requires-Dist: matplotlib
